playground.py
moiptimiser/__init__.py
moiptimiser/__main__.py
moiptimiser/base.py
moiptimiser/cli.py
moiptimiser/impl.py
moiptimiser/ozlen_2014_moiptimiser.py
moiptimiser/tamby_2020_direct_moiptimiser.py
moiptimiser/tamby_2020_moiptimiser.py
moiptimiser/tamby_2020_two_stage_moiptimiser.py
moiptimiser/utilities.py
moiptimiser-0.0.12.dist-info/AUTHORS.rst
moiptimiser-0.0.12.dist-info/LICENSE
moiptimiser-0.0.12.dist-info/METADATA
moiptimiser-0.0.12.dist-info/WHEEL
moiptimiser-0.0.12.dist-info/entry_points.txt
moiptimiser-0.0.12.dist-info/top_level.txt
moiptimiser-0.0.12.dist-info/RECORD
