Metadata-Version: 2.1
Name: moiptimiser
Version: 0.0.12
Summary: Multi-Objective Integer Programming with Gurobi and Python
Home-page: https://github.com/bayan/python-moiptimiser
Author: Bayan Khalili
Author-email: bayan.net@gmail.com
License: MIT
Project-URL: Documentation, https://python-moiptimiser.readthedocs.io/
Project-URL: Changelog, https://python-moiptimiser.readthedocs.io/en/latest/changelog.html
Project-URL: Issue Tracker, https://github.com/bayan/python-moiptimiser/issues
Platform: UNKNOWN
Classifier: Development Status :: 5 - Production/Stable
Classifier: Intended Audience :: Developers
Classifier: License :: OSI Approved :: MIT License
Classifier: Operating System :: Unix
Classifier: Operating System :: POSIX
Classifier: Programming Language :: Python :: 3.9
Classifier: Topic :: Utilities
Requires-Python: >=3.7
License-File: LICENSE
License-File: AUTHORS.rst
Requires-Dist: click
